ppf/__init__.py
ppf/__main__.py
ppf/detector.py
ppf/hierarchical.py
ppf/hybrid.py
ppf/residual_layer.py
ppf/symbolic.py
ppf/symbolic_types.py
ppf/symbolic_utils.py
ppf/types.py
ppf/utils.py
ppf/cli/__init__.py
ppf/cli/main.py
ppf/cli/utils.py
ppf/cli/commands/__init__.py
ppf/cli/commands/detect.py
ppf/cli/commands/discover.py
ppf/cli/commands/export.py
ppf/cli/commands/features.py
ppf/cli/commands/hierarchy.py
ppf/cli/commands/hybrid.py
ppf/cli/commands/info.py
ppf/cli/commands/stack.py
ppf/export/__init__.py
ppf/export/c_export.py
ppf/export/json_export.py
ppf/export/load.py
ppf/export/python_export.py
ppf/features/__init__.py
ppf/features/extract.py
ppf/features/vectorize.py
timeseries_formula_finder-0.2.0.dist-info/licenses/LICENSE
timeseries_formula_finder-0.2.0.dist-info/METADATA
timeseries_formula_finder-0.2.0.dist-info/WHEEL
timeseries_formula_finder-0.2.0.dist-info/entry_points.txt
timeseries_formula_finder-0.2.0.dist-info/top_level.txt
timeseries_formula_finder-0.2.0.dist-info/RECORD
