Metadata-Version: 2.4
Name: timeseries-formula-finder
Version: 0.2.0
Summary: Symbolic Form Discovery - Find interpretable mathematical formulas in data
Author-email: Edward Chalk <edward@fleetingswallow.com>
License-Expression: MIT
Project-URL: Homepage, https://fleetingswallow.com
Project-URL: Repository, https://github.com/pcoz/timeseries-formula-finder
Project-URL: Documentation, https://github.com/pcoz/timeseries-formula-finder#readme
Keywords: symbolic-regression,form-discovery,interpretable-ml,edge-ai,signal-processing,genetic-programming,formula-discovery
Classifier: Development Status :: 3 - Alpha
Classifier: Intended Audience :: Science/Research
Classifier: Operating System :: OS Independent
Classifier: Programming Language :: Python :: 3
Classifier: Programming Language :: Python :: 3.8
Classifier: Programming Language :: Python :: 3.9
Classifier: Programming Language :: Python :: 3.10
Classifier: Programming Language :: Python :: 3.11
Classifier: Programming Language :: Python :: 3.12
Classifier: Topic :: Scientific/Engineering
Classifier: Topic :: Scientific/Engineering :: Information Analysis
Requires-Python: >=3.8
License-File: LICENSE
Requires-Dist: numpy>=1.20.0
Requires-Dist: scipy>=1.7.0
Provides-Extra: hybrid
Requires-Dist: EMD-signal>=1.4.0; extra == "hybrid"
Provides-Extra: dev
Requires-Dist: pytest>=7.0.0; extra == "dev"
Requires-Dist: pytest-cov>=4.0.0; extra == "dev"
Provides-Extra: all
Requires-Dist: EMD-signal>=1.4.0; extra == "all"
Requires-Dist: pytest>=7.0.0; extra == "all"
Requires-Dist: pytest-cov>=4.0.0; extra == "all"
Dynamic: license-file
